{
  "schemaVersion": 1,
  "players": {
    "9c249f6f": { "sig": "Tl(48,5831,INPUT)", "nClass": "W_", "sts": 20602, "aliases": ["a6fc27c5"] },
    "4f38b487": { "sig": "Tl(48,5831,INPUT)", "nClass": "W_", "sts": 20602, "aliases": ["1215646b"] },
    "5cabb421": { "sig": "Qp(25,37,INPUT)", "nClass": "W1", "sts": 20606, "aliases": ["94f9ca52"] },
    "9d2ef9ef": { "sig": "v0(35,4499,INPUT)", "nClass": "uY", "sts": 20607, "aliases": ["6fb43da5"] },
    "69e2a55d": { "sig": "Jf(20,3699,INPUT)", "nClass": "iE", "sts": 20611, "aliases": ["70d8066f"] },
    "ce74690f": { "sig": "$9(2,6487,INPUT)", "nClass": "cV", "sts": 20612, "aliases": ["a5669e32"] },
    "16ee6936": { "sig": "mP(4,155,INPUT)", "nClass": "Yx", "sts": 20613, "aliases": ["ca366632"] },
    "6b8eecd5": { "sig": "mP(4,155,INPUT)", "nClass": "Yx", "sts": 20613, "aliases": ["6ea478fa"] },
    "445213fb": { "sig": "mP(4,155,INPUT)", "nClass": "Yx", "sts": 20613, "aliases": ["d62bd338"] },
    "a32660fc": { "sig": "mP(4,155,INPUT)", "nClass": "Yx", "sts": 20613, "aliases": ["e786ad71"] },
    "959dabb2": { "sig": "IR(84,305,INPUT)", "nClass": "Ga", "sts": 20614, "aliases": ["79c1b58e"] },
    "bb52fe90": { "sig": "Ez(5,408,INPUT)", "nClass": "Oq", "sts": 20615, "aliases": ["f6046ecd"] },
    "1acfe3aa": { "sig": "na(16,3372,INPUT)", "nClass": "dn", "sts": 20616, "aliases": ["fbcdec38"] },
    "c7119fda": { "sig": "na(16,3372,INPUT)", "nClass": "dn", "sts": 20616, "aliases": ["bfba3b57"] },
    "88c25a98": { "sig": "il(16,3372,INPUT)", "nClass": "e4", "sts": 20616, "aliases": ["62100781"] },
    "712f0810": { "sig": "il(16,3372,INPUT)", "nClass": "e4", "sts": 20616, "aliases": ["02a03f06"] },
    "ae0b654c": { "sig": "Ge(91,8257,INPUT)", "nClass": "bK", "sts": 20618, "aliases": ["efc5f0ec"] },
    "5beb355b": { "sig": "Ge(91,8257,INPUT)", "nClass": "bK", "sts": 20618, "aliases": ["b627b8c4"] },
    "b16e1fcb": { "sig": "bA(6,1281,INPUT)", "nClass": "rr", "sts": 20619, "aliases": ["519ee1b2"] },
    "b04445d4": { "sig": "bA(6,1281,INPUT)", "nClass": "rr", "sts": 20619, "aliases": ["b8dc0882"] },
    "101d8d29": { "sig": "DX(6,1281,INPUT)", "nClass": "bD", "sts": 20619, "aliases": ["d0593fc3"] },
    "8583bbc2": { "sig": "DX(6,1281,INPUT)", "nClass": "bD", "sts": 20619, "aliases": ["cf7c7281"] },
    "302f98ca": { "sig": "DX(6,1281,INPUT)", "nClass": "bD", "sts": 20619, "aliases": ["f0c9d2bf"] },
    "f291f880": { "sig": "BK(15,4053,INPUT)", "nClass": "iz", "sts": 20620, "aliases": ["64628ab1"] },
    "0b359740": { "sig": "BK(15,4053,INPUT)", "nClass": "iz", "sts": 20620, "aliases": ["c902801c"] },
    "f0a916b1": { "sig": "BK(15,4053,INPUT)", "nClass": "iz", "sts": 20620, "aliases": ["9bbe161b"] },
    "ac678d18": { "sig": "BK(15,4053,INPUT)", "nClass": "iz", "sts": 20620, "aliases": ["a6fa4805"] },
    "d2972ab1": { "sig": "U2(4,4595,INPUT)", "nClass": "Mh", "sts": 20621, "aliases": ["917d27d0"] },
    "c0c02e9a": { "sig": "rh(4,4595,INPUT)", "nClass": "T7", "sts": 20621, "aliases": ["a0cedc12"] },
    "3ee6de37": { "sig": "Mh(4,4595,INPUT)", "nClass": "gX", "sts": 20621, "aliases": ["59dc247f"] },
    "1cf32b49": { "sig": "Mh(4,4595,INPUT)", "nClass": "gX", "sts": 20621, "aliases": ["e42f9538"] },
    "c5a9b924": { "sig": "U2(4,4595,INPUT)", "nClass": "Mh", "sts": 20621, "aliases": ["1470b620"] },
    "4d52384b": { "sig": "Mh(4,4595,INPUT)", "nClass": "gX", "sts": 20621, "aliases": ["21274796"] },
    "cb0c1314": { "sig": "Hl(1,8889,INPUT)", "nClass": "Fo", "sts": 20622, "aliases": ["37134aca"] },
    "2f2d5103": { "sig": "Hl(1,8889,INPUT)", "nClass": "Fo", "sts": 20622, "aliases": ["5cedae84"] },
    "06cb0078": { "sig": "Hl(1,8889,INPUT)", "nClass": "Fo", "sts": 20622, "aliases": ["6d75fe32"] },
    "493785e3": { "sig": "Hl(1,8889,INPUT)", "nClass": "Fo", "sts": 20622, "aliases": ["d40e4e01"] },
    "ff01315e": { "sig": "Hl(1,8889,INPUT)", "nClass": "Fo", "sts": 20622, "aliases": ["34c51503"] },
    "f63d2d36": { "sig": "Hl(1,8889,INPUT)", "nClass": "Fo", "sts": 20622, "aliases": ["5af43cdf"] },
    "6925147e": { "sig": "Hl(1,8889,INPUT)", "nClass": "Fo", "sts": 20622, "aliases": ["29debfa6"] },
    "ae9401d3": { "sig": "Hl(1,8889,INPUT)", "nClass": "Fo", "sts": 20622, "aliases": ["9d8190f4"] },
    "13e874d0": { "sig": "Hl(1,8889,INPUT)", "nClass": "Fo", "sts": 20622, "aliases": ["cf5de392"] },
    "5df2936e": { "sig": "Hl(1,8889,INPUT)", "nClass": "Fo", "sts": 20622, "aliases": ["d15cb8b6"] },
    "49c4470a": { "sig": "fJ(24,1210,INPUT)", "nClass": "lq", "sts": 20627, "aliases": ["7fb559ad"] },
    "98e34bc6": { "sig": "fJ(24,1210,INPUT)", "nClass": "lq", "sts": 20627, "aliases": ["8e9265f0"] },
    "676feccc": { "sig": "vb(24,1210,INPUT)", "nClass": "XS", "sts": 20627, "aliases": ["c25a6356"] },
    "5b27766f": { "sig": "fJ(24,1210,INPUT)", "nClass": "lq", "sts": 20627, "aliases": ["c43e5df4"] },
    "eaf70881": { "sig": "fA(27,4578,INPUT)", "nClass": "yF", "sts": 20628, "aliases": ["0034697e"] },
    "b0fec6e9": { "sig": "fA(27,4578,INPUT)", "nClass": "yF", "sts": 20628, "aliases": ["e38fa4ea"] },
    "00ee7c1b": { "sig": "fA(27,4578,INPUT)", "nClass": "yF", "sts": 20628, "aliases": ["107f9aee"] },
    "c81e9886": { "sig": "fA(27,4578,INPUT)", "nClass": "yF", "sts": 20628, "aliases": ["4cacaa47"] },
    "b0e668dc": { "sig": "fA(27,4578,INPUT)", "nClass": "yF", "sts": 20628, "aliases": ["dc83dfe9"] },
    "7316706d": { "sig": "fA(27,4578,INPUT)", "nClass": "yF", "sts": 20628, "aliases": ["cb4a6ace"] },
    "7a37f05b": { "sig": "fA(27,4578,INPUT)", "nClass": "yF", "sts": 20628, "aliases": ["65a16e87"] },
    "edf92b2c": { "sig": "Re(18,3515,INPUT)", "nClass": "Fs", "sts": 20629, "aliases": ["651cb74c"] },
    "e2b516fb": { "sig": "dV(18,3515,INPUT)", "nClass": "$x", "sts": 20629, "aliases": ["8a064c1f"] },
    "a66f5a13": { "sig": "Re(18,3515,INPUT)", "nClass": "Fs", "sts": 20629, "aliases": ["35116500"] },
    "9adea8e3": { "sig": "Re(18,3515,INPUT)", "nClass": "Fs", "sts": 20629, "aliases": ["1a7c09f2"] },
    "a85504a6": { "sig": "WE(1,878,INPUT)", "nClass": "TR", "sts": 20630, "aliases": ["f1fcf242"] },
    "030cd809": { "sig": "WE(1,878,INPUT)", "nClass": "TR", "sts": 20630, "aliases": ["a52293fb"] },
    "5d75c2e1": { "sig": "ci(21,5350,INPUT)", "nClass": "of", "sts": 20632, "aliases": ["74472930"] },
    "4918c89a": { "sig": "ci(21,5350,INPUT)", "nClass": "of", "sts": 20632, "aliases": ["a31e029d"] },
    "5728051c": { "sig": "ci(21,5350,INPUT)", "nClass": "of", "sts": 20632, "aliases": ["c983821c"] },
    "6dc2ce7c": { "sig": "oU(3,4568,INPUT)", "nClass": "kr", "sts": 20633, "aliases": ["494c3813"] },
    "a152cbd5": { "sig": "oU(3,4568,INPUT)", "nClass": "kr", "sts": 20633, "aliases": ["90141e95"] },
    "8b4164f6": { "sig": "oU(3,4568,INPUT)", "nClass": "kr", "sts": 20633, "aliases": ["aebab366"] },
    "0053e6c9": { "sig": "zf(3,4568,INPUT)", "nClass": "B3", "sts": 20633, "aliases": ["24933d5f"] },
    "1e84899c": { "sig": "b$(1,8150,INPUT)", "nClass": "ee", "sts": 20634, "aliases": ["78e065bd"] },
    "6ec31678": { "sig": "ST(1,8150,INPUT)", "nClass": "oO", "sts": 20634, "aliases": ["9ee35aff"] },
    "f5fbaad8": { "sig": "ST(1,8150,INPUT)", "nClass": "oO", "sts": 20634, "aliases": ["91dcbffc"] },
    "a9fe4815": { "sig": "ST(1,8150,INPUT)", "nClass": "oO", "sts": 20634, "aliases": ["6a33e5c2"] },
    "13792696": { "sig": "ST(1,8150,INPUT)", "nClass": "oO", "sts": 20634, "aliases": ["5ff90ebf"] },
    "6009b507": { "sig": "ST(1,8150,INPUT)", "nClass": "oO", "sts": 20634, "aliases": ["4eab840f"] },
    "f551602d": { "sig": "vR(5,6110,INPUT)", "nClass": "Vg", "sts": 20639, "aliases": ["f474e1c9"] },
    "74ac8690": { "sig": "vR(5,6110,INPUT)", "nClass": "Vg", "sts": 20639, "aliases": ["42275f80"] },
    "5fa5b166": { "sig": "C3(15,933,INPUT)", "nClass": "WM", "sts": 20640, "aliases": ["605c82cc"] },
    "e43c0a19": { "sig": "C3(15,933,INPUT)", "nClass": "WM", "sts": 20640, "aliases": ["b889c248"] },
    "f74306f1": { "sig": "C3(15,933,INPUT)", "nClass": "WM", "sts": 20640, "aliases": ["02b9c756"] },
    "ecd4b80a": { "sig": "C3(15,933,INPUT)", "nClass": "WM", "sts": 20640, "aliases": ["287c3986"] },
    "63173e4a": { "sig": "C3(15,933,INPUT)", "nClass": "WM", "sts": 20640, "aliases": ["9a6963a1"] },
    "72d9c776": { "sig": "C3(15,933,INPUT)", "nClass": "WM", "sts": 20640, "aliases": ["6088fc9a"] },
    "636ed5b5": { "sig": "C3(15,933,INPUT)", "nClass": "WM", "sts": 20640, "aliases": ["08285b84"] },
    "04b89b89": { "sig": "C3(15,933,INPUT)", "nClass": "WM", "sts": 20640, "aliases": ["52d279e1"] },
    "71b152e7": { "sig": "C3(15,933,INPUT)", "nClass": "WM", "sts": 20640, "aliases": ["6b406097"] },
    "e2701c55": { "sig": "C3(15,933,INPUT)", "nClass": "WM", "sts": 20640, "aliases": ["4244ab07"] },
    "80760a82": { "sig": "C3(15,933,INPUT)", "nClass": "WM", "sts": 20640, "aliases": ["a896e611"] },
    "e30d74e3": { "sig": "C3(15,933,INPUT)", "nClass": "WM", "sts": 20640, "aliases": ["5ae55ea6"] },
    "d79fb9f8": { "sig": "C3(15,933,INPUT)", "nClass": "WM", "sts": 20640, "aliases": ["90aa6fe4"] },
    "66a6ea83": { "sig": "C3(15,933,INPUT)", "nClass": "WM", "sts": 20640, "aliases": ["2afc9693"] },
    "b2466c24": { "sig": "Pj(5,7018,INPUT)", "nClass": "nI", "sts": 20642, "aliases": ["5b205b4d"] },
    "dd53c628": { "sig": "xz(5,7018,INPUT)", "nClass": "cY", "sts": 20642, "aliases": ["82a3b15e"] }
  }
}
